py_nightscout/__init__.py
py_nightscout/api.py
py_nightscout/models.py
py_nightscout-1.3.3.dist-info/METADATA
py_nightscout-1.3.3.dist-info/WHEEL
py_nightscout-1.3.3.dist-info/top_level.txt
py_nightscout-1.3.3.dist-info/RECORD
