Metadata-Version: 2.1
Name: py-nightscout
Version: 1.3.3
Summary: A library that provides a Python async interface to Nightscout
Home-page: https://github.com/marciogranzotto/py-nightscout
Author: Marcio Granzotto
Author-email: marciogranzotto@gmail.com
License: MIT
Keywords: nightscout api client development
Platform: UNKNOWN
Classifier: Intended Audience :: Developers
Classifier: Topic :: Software Development :: Libraries :: Python Modules
Classifier: License :: OSI Approved :: MIT License
Classifier: Programming Language :: Python :: 3
Requires-Dist: python-dateutil
Requires-Dist: pytz
Requires-Dist: aiohttp (>=3.6.1)
